spotidry/__init__.py
spotidry/__main__.py
spotidry/cli.py
spotidry/spotify.py
spotidry-0.0.9.dist-info/METADATA
spotidry-0.0.9.dist-info/WHEEL
spotidry-0.0.9.dist-info/entry_points.txt
spotidry-0.0.9.dist-info/licenses/LICENSE
spotidry-0.0.9.dist-info/RECORD
