Metadata-Version: 2.4
Name: spotidry
Version: 0.0.9
Summary: A boring Spotify CLI client
Project-URL: Homepage, https://github.com/mikeboiko/spotidry
Project-URL: Bug Tracker, https://github.com/mikeboiko/spotidry/issues
Author-email: Mike Boiko <mike@boiko.ca>
License-File: LICENSE
Classifier: License :: OSI Approved :: MIT License
Classifier: Operating System :: OS Independent
Classifier: Programming Language :: Python :: 3
Requires-Python: >=3.10
Requires-Dist: appdirs
Requires-Dist: basedpyright
Requires-Dist: pyyaml
Requires-Dist: spotipy
Provides-Extra: test
Requires-Dist: pytest; extra == 'test'
